json_stream_generator/VERSION
json_stream_generator/__init__.py
json_stream_generator/rest_framework/__init__.py
json_stream_generator/rest_framework/mixins.py
json_stream_generator-0.2.0.dist-info/METADATA
json_stream_generator-0.2.0.dist-info/WHEEL
json_stream_generator-0.2.0.dist-info/top_level.txt
json_stream_generator-0.2.0.dist-info/RECORD
