Metadata-Version: 2.1
Name: json-stream-generator
Version: 0.2.0
Summary: json-stream-generator - serialize json to stream of strings in generator
Home-page: http://github.com/wlatanowicz/json-stream-generator
Author: Wiktor Latanowicz
Author-email: json-stream-generator@wiktor.latanowicz.com
License: MIT
Classifier: Programming Language :: Python :: 3
Classifier: License :: OSI Approved :: MIT License
Classifier: Operating System :: OS Independent
Requires-Python: >=3.6
